CHANGES.txt
bootstrap.py
buildout.cfg
setup.py
src/ldapadapter/README.txt
src/ldapadapter/TODO.txt
src/ldapadapter/__init__.py
src/ldapadapter/check.py
src/ldapadapter/configure.zcml
src/ldapadapter/field.py
src/ldapadapter/i18n.py
src/ldapadapter/interfaces.py
src/ldapadapter/utility.py
src/ldapadapter.egg-info/PKG-INFO
src/ldapadapter.egg-info/SOURCES.txt
src/ldapadapter.egg-info/dependency_links.txt
src/ldapadapter.egg-info/not-zip-safe
src/ldapadapter.egg-info/requires.txt
src/ldapadapter.egg-info/top_level.txt
src/ldapadapter/browser/__init__.py
src/ldapadapter/browser/check.pt
src/ldapadapter/browser/check.py
src/ldapadapter/browser/configure.zcml
src/ldapadapter/help/__init__.py
src/ldapadapter/help/ldapadapter.stx
src/ldapadapter/tests/__init__.py
src/ldapadapter/tests/fakeldap.py
src/ldapadapter/tests/test_field.py
src/ldapadapter/tests/test_ldapadapter.py