Metadata-Version: 1.0
Name: ldapadapter
Version: 0.8
Summary: LDAP connection for Zope Toolkit. Connects to an LDAP server.
